aiLinter.py
ai_linter-0.1.1.dist-info/licenses/LICENSE
lib/__init__.py
lib/config.py
lib/log.py
lib/parser.py
lib/py.typed
processors/__init__.py
processors/process_agents.py
processors/process_skills.py
processors/py.typed
validators/__init__.py
validators/agent_validator.py
validators/file_reference_validator.py
validators/front_matter_validator.py
validators/py.typed
validators/skill_validator.py
ai_linter-0.1.1.dist-info/METADATA
ai_linter-0.1.1.dist-info/WHEEL
ai_linter-0.1.1.dist-info/entry_points.txt
ai_linter-0.1.1.dist-info/top_level.txt
ai_linter-0.1.1.dist-info/RECORD
