Metadata-Version: 2.4
Name: ai-linter
Version: 0.1.1
Summary: A validation tool for AI skills and agent configurations
Author: François Chastanet
License-Expression: MIT
Project-URL: Homepage, https://github.com/fchastanet/ai-linter
Project-URL: Repository, https://github.com/fchastanet/ai-linter.git
Project-URL: Issues, https://github.com/fchastanet/ai-linter/issues
Keywords: ai,linter,validation,skills,agents
Classifier: Development Status :: 3 - Alpha
Classifier: Intended Audience :: Developers
Classifier: Operating System :: OS Independent
Classifier: Programming Language :: Python :: 3
Classifier: Programming Language :: Python :: 3.10
Classifier: Programming Language :: Python :: 3.11
Classifier: Programming Language :: Python :: 3.12
Classifier: Topic :: Software Development :: Quality Assurance
Classifier: Topic :: Software Development :: Testing
Requires-Python: >=3.10
License-File: LICENSE
Requires-Dist: tiktoken>=0.5.0
Requires-Dist: PyYAML>=6.0
Requires-Dist: pyparsing>=3.0.0
Provides-Extra: dev
Requires-Dist: black>=23.0.0; extra == "dev"
Requires-Dist: isort>=5.12.0; extra == "dev"
Requires-Dist: flake8>=6.0.0; extra == "dev"
Requires-Dist: mypy>=1.0.0; extra == "dev"
Requires-Dist: pytest>=7.0.0; extra == "dev"
Requires-Dist: pytest-cov>=4.0.0; extra == "dev"
Requires-Dist: pre-commit>=3.0.0; extra == "dev"
Requires-Dist: build>=0.8.0; extra == "dev"
Requires-Dist: twine>=4.0.0; extra == "dev"
Dynamic: license-file
